LexStruct_PDF/__init__.py
LexStruct_PDF/content_extractor.py
lexstruct_pdf-0.0.1.dist-info/LICENSE
lexstruct_pdf-0.0.1.dist-info/METADATA
lexstruct_pdf-0.0.1.dist-info/WHEEL
lexstruct_pdf-0.0.1.dist-info/top_level.txt
lexstruct_pdf-0.0.1.dist-info/RECORD
