Metadata-Version: 2.1
Name: lexstruct_pdf
Version: 0.0.1
Summary: A package that enables extraction of text, images, and tables.
Author-email: "LexStruct(Anurag Yadav)" <anurag.y2599@outlook.com>
Keywords: python,PDF,extract,text,tables,images,LexStruct
Classifier: Intended Audience :: Developers
Classifier: Programming Language :: Python :: 3
Classifier: Operating System :: MacOS :: MacOS X
Classifier: Operating System :: Microsoft :: Windows
Requires-Python: >=3.8
License-File: LICENSE
Requires-Dist: PyMuPDF
